dfDewey-20231016.data/data/share/doc/dfdewey/AUTHORS
dfDewey-20231016.data/data/share/doc/dfdewey/LICENSE
dfDewey-20231016.data/data/share/doc/dfdewey/README.md
dfdewey/__init__.py
dfdewey/dfdcli.py
dfdewey/config/__init__.py
dfdewey/config/config_template.py
dfdewey/datastore/__init__.py
dfdewey/datastore/opensearch.py
dfdewey/datastore/postgresql.py
dfdewey/utils/__init__.py
dfdewey/utils/image_processor.py
dfdewey/utils/index_searcher.py
dfDewey-20231016.dist-info/LICENSE
dfDewey-20231016.dist-info/METADATA
dfDewey-20231016.dist-info/WHEEL
dfDewey-20231016.dist-info/entry_points.txt
dfDewey-20231016.dist-info/top_level.txt
dfDewey-20231016.dist-info/RECORD
