Metadata-Version: 2.1
Name: dfDewey
Version: 20231016
Summary: dfDewey is a digital forensics string extraction, indexing, and searching tool.
Home-page: https://github.com/google/dfdewey
Maintainer: dfDewey development team
Maintainer-email: dfdewey-dev@googlegroups.com
License: Apache License, Version 2.0
Classifier: Development Status :: 3 - Alpha
Classifier: Environment :: Console
Classifier: Operating System :: OS Independent
Classifier: Programming Language :: Python :: 3
Requires-Python: >=3.6
License-File: LICENSE
Requires-Dist: opensearch-py
Requires-Dist: psycopg2-binary
Requires-Dist: six
Requires-Dist: tabulate
Provides-Extra: dev
Requires-Dist: mock ; extra == 'dev'
Requires-Dist: pytest ; extra == 'dev'
Requires-Dist: yapf ; extra == 'dev'
Requires-Dist: coverage ; extra == 'dev'
